{
  "schemaVersion": 1,
  "id": "shape-ref-summing-junction",
  "title": "Summing Junction — anchors & text slot",
  "mode": "diagram",
  "viewport": {
    "x": 0,
    "y": 0,
    "zoom": 1
  },
  "size": {
    "width": 498,
    "height": 498
  },
  "objects": [
    {
      "id": "subject-summing-junction",
      "type": "summing-junction",
      "label": "Summing Junction",
      "geometry": {
        "x": 160,
        "y": 160,
        "width": 100,
        "height": 100
      }
    },
    {
      "id": "marker-summing-junction-top",
      "type": "text",
      "label": "top",
      "geometry": {
        "x": 178,
        "y": 57,
        "width": 64,
        "height": 28
      }
    },
    {
      "id": "marker-summing-junction-right",
      "type": "text",
      "label": "right",
      "geometry": {
        "x": 335,
        "y": 196,
        "width": 64,
        "height": 28
      }
    },
    {
      "id": "marker-summing-junction-bottom",
      "type": "text",
      "label": "bottom",
      "geometry": {
        "x": 178,
        "y": 335,
        "width": 64,
        "height": 28
      }
    },
    {
      "id": "marker-summing-junction-left",
      "type": "text",
      "label": "left",
      "geometry": {
        "x": 21,
        "y": 196,
        "width": 64,
        "height": 28
      }
    },
    {
      "id": "note-summing-junction",
      "type": "text",
      "label": "no visible label text is rendered for summing-junction (accessibility-only; hidesVisibleText); silhouette is a circle with an inscribed x",
      "geometry": {
        "x": 120,
        "y": 403,
        "width": 180,
        "height": 32
      }
    }
  ],
  "connections": [
    {
      "id": "conn-summing-junction-top",
      "from": {
        "objectId": "marker-summing-junction-top",
        "anchor": "center"
      },
      "to": {
        "objectId": "subject-summing-junction",
        "anchor": "top",
        "position": [
          0.5,
          0
        ]
      },
      "style": "solid",
      "arrow": "forward"
    },
    {
      "id": "conn-summing-junction-right",
      "from": {
        "objectId": "marker-summing-junction-right",
        "anchor": "center"
      },
      "to": {
        "objectId": "subject-summing-junction",
        "anchor": "right",
        "position": [
          1,
          0.5
        ]
      },
      "style": "solid",
      "arrow": "forward"
    },
    {
      "id": "conn-summing-junction-bottom",
      "from": {
        "objectId": "marker-summing-junction-bottom",
        "anchor": "center"
      },
      "to": {
        "objectId": "subject-summing-junction",
        "anchor": "bottom",
        "position": [
          0.5,
          1
        ]
      },
      "style": "solid",
      "arrow": "forward"
    },
    {
      "id": "conn-summing-junction-left",
      "from": {
        "objectId": "marker-summing-junction-left",
        "anchor": "center"
      },
      "to": {
        "objectId": "subject-summing-junction",
        "anchor": "left",
        "position": [
          0,
          0.5
        ]
      },
      "style": "solid",
      "arrow": "forward"
    }
  ],
  "links": [],
  "annotations": []
}
